fy_common_ext/__init__.py
fy_common_ext/iter_utils.py
fy_common_ext/containers/__init__.py
fy_common_ext/containers/configuration.py
fy_common_ext/core/__init__.py
fy_common_ext/core/list_utils.py
fy_common_ext/core/str_utils.py
fy_common_ext/io/__init__.py
fy_common_ext/io/io_wrappers.py
fy_common_ext-0.1.0.dist-info/LICENSE
fy_common_ext-0.1.0.dist-info/METADATA
fy_common_ext-0.1.0.dist-info/WHEEL
fy_common_ext-0.1.0.dist-info/top_level.txt
fy_common_ext-0.1.0.dist-info/RECORD
