Metadata-Version: 2.1
Name: fy-common-ext
Version: 0.1.0
Summary: Some common extensions of Python
Home-page: https://github.com/fyabc/SmallTools/tree/master/Python/fy_common_ext
Author: fyabc
Author-email: fyabc95@gmail.com
License: UNKNOWN
Platform: UNKNOWN
Classifier: Programming Language :: Python :: 3
Classifier: License :: OSI Approved :: MIT License
Classifier: Operating System :: OS Independent
Requires-Python: >=3.6
License-File: LICENSE
